gryphon/__init__.py
gryphon/dashboards/__init__.py
gryphon/dashboards/alembic.ini
gryphon/dashboards/app.py
gryphon/dashboards/routes.py
gryphon/dashboards/settings.py
gryphon/dashboards/uimodules.py
gryphon/dashboards/handlers/__init__.py
gryphon/dashboards/handlers/admin_base.py
gryphon/dashboards/handlers/assets.py
gryphon/dashboards/handlers/balances.py
gryphon/dashboards/handlers/base.py
gryphon/dashboards/handlers/block_times.py
gryphon/dashboards/handlers/fees.py
gryphon/dashboards/handlers/home.py
gryphon/dashboards/handlers/ledger.py
gryphon/dashboards/handlers/login.py
gryphon/dashboards/handlers/logout.py
gryphon/dashboards/handlers/notfound.py
gryphon/dashboards/handlers/status.py
gryphon/dashboards/handlers/tick_times.py
gryphon/dashboards/handlers/trade_view.py
gryphon/dashboards/handlers/mixins/__init__.py
gryphon/dashboards/handlers/mixins/active_exchanges.py
gryphon/dashboards/handlers/mixins/start_and_end_time.py
gryphon/dashboards/handlers/orderbooks/__init__.py
gryphon/dashboards/handlers/orderbooks/defaults.py
gryphon/dashboards/handlers/orderbooks/orderbook.py
gryphon/dashboards/handlers/strategies/__init__.py
gryphon/dashboards/handlers/strategies/builtin_configs.py
gryphon/dashboards/handlers/strategies/strategy.py
gryphon/dashboards/migrations/__init__.py
gryphon/dashboards/migrations/env.py
gryphon/dashboards/migrations/versions/5169cd803822_initial_migration.py
gryphon/dashboards/models/__init__.py
gryphon/dashboards/models/base.py
gryphon/dashboards/models/user.py
gryphon/dashboards/models/columns/__init__.py
gryphon/dashboards/models/columns/password_column.py
gryphon/dashboards/static/favicon.ico
gryphon/dashboards/static/css/main.css
gryphon/dashboards/static/css/strategy.css
gryphon/dashboards/static/img/gryphon-logo-blue-square.png
gryphon/dashboards/static/img/gryphon-logo-blue-square@2x.png
gryphon/dashboards/static/img/gryphon-logo-blue-square@3x.png
gryphon/dashboards/static/img/gryphon-logo-blue-wide.png
gryphon-0.11.2.dist-info/LICENSE
gryphon-0.11.2.dist-info/METADATA
gryphon-0.11.2.dist-info/WHEEL
gryphon-0.11.2.dist-info/entry_points.txt
gryphon-0.11.2.dist-info/top_level.txt
gryphon-0.11.2.dist-info/RECORD
