Metadata-Version: 2.1
Name: gryphon
Version: 0.11.2
Summary: A framework for running algorithmic trading strategies on cryptocurrency markets.
Home-page: http://www.gryphonframework.org
Author: MacLeod & Robinson, Inc.
Author-email: hello@tinkercorp.com
License: UNKNOWN
Platform: UNKNOWN
Classifier: Programming Language :: Python :: 2.7
Classifier: Operating System :: OS Independent
Classifier: License :: Other/Proprietary License
Requires-Dist: alembic (==0.6.0)
Requires-Dist: Babel (==2.6.0)
Requires-Dist: backports.shutil-get-terminal-size (==1.0.0)
Requires-Dist: cement (==2.10.12)
Requires-Dist: certifi (==2018.4.16)
Requires-Dist: chardet (==3.0.4)
Requires-Dist: coinbase (==1.0.4)
Requires-Dist: contextlib2 (==0.5.5)
Requires-Dist: Cython (==0.20.1)
Requires-Dist: decorator (==4.3.0)
Requires-Dist: Delorean (<2,>=1.0.0)
Requires-Dist: enum34 (==1.1.6)
Requires-Dist: futures (==3.2.0)
Requires-Dist: gryphon-cdecimal (==2.3)
Requires-Dist: gryphon-money
Requires-Dist: gryphon-pusherclient
Requires-Dist: idna (==2.7)
Requires-Dist: ipython (==5.7.0)
Requires-Dist: ipython-genutils (==0.2.0)
Requires-Dist: line-profiler (==2.1.2)
Requires-Dist: Mako (==1.0.7)
Requires-Dist: MarkupSafe (==1.0)
Requires-Dist: mock (==1.0.1)
Requires-Dist: more-itertools (<5,>=4.2.0)
Requires-Dist: MySQL-python (==1.2.5)
Requires-Dist: nose (==1.3.7)
Requires-Dist: pathlib2 (==2.3.2)
Requires-Dist: pexpect (==4.6.0)
Requires-Dist: pickleshare (==0.7.4)
Requires-Dist: prompt-toolkit (==1.0.15)
Requires-Dist: ptyprocess (==0.6.0)
Requires-Dist: Pygments (==2.2.0)
Requires-Dist: pylibmc (<2,>=1.5.2)
Requires-Dist: python-dotenv (==0.8.2)
Requires-Dist: pytz (==2018.5)
Requires-Dist: raven (==6.9.0)
Requires-Dist: rednose (<2,>=1.3.0)
Requires-Dist: redis (==2.10.6)
Requires-Dist: requests (==2.19.1)
Requires-Dist: requests-futures (==0.9.7)
Requires-Dist: requests-toolbelt (==0.8.0)
Requires-Dist: retrying (==1.3.3)
Requires-Dist: scandir (==1.7)
Requires-Dist: simplegeneric (==0.8.1)
Requires-Dist: six (==1.11.0)
Requires-Dist: sure (==1.2.9)
Requires-Dist: SQLAlchemy (<1.3,>=1.2.10)
Requires-Dist: termcolor (==1.1.0)
Requires-Dist: traitlets (==4.3.2)
Requires-Dist: tzlocal (==1.5.1)
Requires-Dist: urllib3 (==1.23)
Requires-Dist: wcwidth (==0.1.7)
Requires-Dist: websocket-client (==0.48.0)
